velodata-1.7.1.dist-info/METADATA
velodata-1.7.1.dist-info/WHEEL
velodata-1.7.1.dist-info/entry_points.txt
velodata-1.7.1.dist-info/licenses/LICENSE
velodata/__init__.py
velodata/example.py
velodata/example_news.py
velodata/lib.py
velodata-1.7.1.dist-info/RECORD
