Metadata-Version: 2.1
Name: velodata
Version: 1.7.1
Summary: Python library for interacting with the Velo Data API
Author-Email: Velo Data <support@velodata.app>
Classifier: Programming Language :: Python :: 3
Classifier: License :: OSI Approved :: MIT License
Classifier: Operating System :: OS Independent
Project-URL: GitHub, https://github.com/velodataorg/velo-python
Project-URL: Docs, https://velodata.gitbook.io/velo-data-api/python
Requires-Python: >=3.0
Requires-Dist: pandas
Requires-Dist: requests
Requires-Dist: websockets
Requires-Dist: asyncio
